<?xml version="1.0"?>
<menu>
  <item>
    <path>civicrm/pcp/page</path>
    <page_callback>CRM_Pcpteams_Page_PCP</page_callback>
    <title>Personal Campaign Page</title>
    <access_callback>1</access_callback>
    <is_public>true</is_public>
  </item>
  <item>
     <path>civicrm/pcp/support</path>
     <title>Personal Campaign Page - Account Information</title>
     <page_callback>CRM_Pcpteams_Controller_PCP</page_callback>
     <access_arguments>register for events</access_arguments>
     <is_public>true</is_public>
     <weight>0</weight>
  </item>
  <item>
    <path>civicrm/pcp/dashboard</path>
    <page_callback>CRM_Pcpteams_Page_Dashboard</page_callback>
    <title>My Dashboard</title>
    <access_arguments>access CiviCRM</access_arguments>
  </item>
  <item>
    <path>civicrm/pcp/profile</path>
    <page_callback>CRM_Pcpteams_Form_ProfilePic</page_callback>
    <title>Profile Pic</title>
    <access_arguments>access CiviCRM</access_arguments>
  </item>
  <item>
    <path>civicrm/pcp/manage</path>
    <page_callback>CRM_Pcpteams_Form_PCP_Manage</page_callback>
    <title>Update Personal Campaign Page</title>
    <access_arguments>access CiviCRM</access_arguments>
  </item>
  <item>
    <path>civicrm/pcp/inline/edit</path>
    <page_callback>CRM_Pcpteams_Form_PCP_InlineEditTeam</page_callback>
    <title>Update Personal Campaign Page</title>
    <access_arguments>access CiviCRM</access_arguments>
  </item>
</menu>
